{
    "blood_group": "O+",
    "bags_needed": "1",
    "mediator": {
        "username": ""
    },
    "patient": {
        "name": "",
        "age-group": ""
    },
    "condition": "",
    "location": "Kidney hospital, Mirpur",
    "probable_day": "",
    "probable_time": "",
    "contacts": [
        {
            "name": "",
            "contact_numbers": [
                ""
            ],
            "relation_with_patient": "Amar friend er mamar jonno"
        }
    ],
    "compensation": {
        "transportation": "",
        "allowance": ""
    }
}